cfn_drift_remediation/__init__.py
cfn_drift_remediation/aws_error_utils.py
cfn_drift_remediation/cli.py
cfn_drift_remediation/cli_exceptions.py
cfn_drift_remediation/utils.py
cfn_drift_remediation-0.3.1.dist-info/entry_points.txt
cfn_drift_remediation-0.3.1.dist-info/LICENSE
cfn_drift_remediation-0.3.1.dist-info/WHEEL
cfn_drift_remediation-0.3.1.dist-info/METADATA
cfn_drift_remediation-0.3.1.dist-info/RECORD
